tom_nonlocalizedevents/__init__.py
tom_nonlocalizedevents/admin.py
tom_nonlocalizedevents/alertstream_handlers/__init__.py
tom_nonlocalizedevents/alertstream_handlers/gcn_event_handler.py
tom_nonlocalizedevents/alertstream_handlers/igwn_event_handler.py
tom_nonlocalizedevents/apps.py
tom_nonlocalizedevents/healpix_utils.py
tom_nonlocalizedevents/ingestion.py
tom_nonlocalizedevents/migrations/0001_initial.py
tom_nonlocalizedevents/migrations/0002_superevent.py
tom_nonlocalizedevents/migrations/0003_auto_20210225_0034.py
tom_nonlocalizedevents/migrations/0004_superevent_superevent_type.py
tom_nonlocalizedevents/migrations/0005_auto_20210319_2241.py
tom_nonlocalizedevents/migrations/0006_auto_20210827_2346.py
tom_nonlocalizedevents/migrations/0007_eventcandidate_viable.py
tom_nonlocalizedevents/migrations/0008_eventcandidate_priority.py
tom_nonlocalizedevents/migrations/0009_rename_superevent_nonlocalizedevent.py
tom_nonlocalizedevents/migrations/0010_rename_more_superevent_fields.py
tom_nonlocalizedevents/migrations/0011_eventcandidate_viability_reason_and_more.py
tom_nonlocalizedevents/migrations/0012_nonlocalizedevent_event_subtype.py
tom_nonlocalizedevents/migrations/0013_eventcandidate_healpix_and_more.py
tom_nonlocalizedevents/migrations/0014_credibleregion_and_more.py
tom_nonlocalizedevents/migrations/0015_eventsequence_and_more.py
tom_nonlocalizedevents/migrations/0016_externalcoincidence_alter_eventsequence_options_and_more.py
tom_nonlocalizedevents/migrations/0017_alter_eventsequence_external_coincidence_and_more.py
tom_nonlocalizedevents/migrations/0018_alter_eventlocalization_date.py
tom_nonlocalizedevents/migrations/__init__.py
tom_nonlocalizedevents/models.py
tom_nonlocalizedevents/serializers.py
tom_nonlocalizedevents/signals/__init__.py
tom_nonlocalizedevents/signals/handlers.py
tom_nonlocalizedevents/static/tom_nonlocalizedevents/css/main.css
tom_nonlocalizedevents/static/tom_nonlocalizedevents/vue/css/superevent_vue_app.css
tom_nonlocalizedevents-0.9.0.dist-info/LICENSE
tom_nonlocalizedevents-0.9.0.dist-info/METADATA
tom_nonlocalizedevents-0.9.0.dist-info/WHEEL
tom_nonlocalizedevents-0.9.0.dist-info/RECORD
