Metadata-Version: 2.3
Name: tom-nonlocalizedevents
Version: 0.9.0
Summary: Reusable TOMToolkit app to support gravitational wave superevent and other nonlocalized event EM follow-up observations.
License: GPL-3.0-only
Keywords: tomtoolkit,astronomy,astrophysics,cosmology,science
Author: TOM Toolkit Project
Author-email: tomtoolkit-maintainers@lco.global
Maintainer: William Lindstrom
Maintainer-email: llindstrom@lco.global
Requires-Python: >=3.10,<3.13
Classifier: Environment :: Web Environment
Classifier: Framework :: Django
Classifier: Framework :: Django :: 4.1
Classifier: Intended Audience :: Developers
Classifier: Intended Audience :: Science/Research
Classifier: License :: OSI Approved :: GNU General Public License v3 or later (GPLv3+)
Classifier: Operating System :: OS Independent
Classifier: Programming Language :: Python
Classifier: Programming Language :: Python :: 3
Classifier: Programming Language :: Python :: 3 :: Only
Classifier: Programming Language :: Python :: 3.10
Classifier: Programming Language :: Python :: 3.11
Classifier: Programming Language :: Python :: 3.12
Classifier: Topic :: Scientific/Engineering :: Astronomy
Classifier: Topic :: Scientific/Engineering :: Physics
Requires-Dist: MOCPy (>=0.17.0,<1.0)
Requires-Dist: SQLAlchemy (>=2.0.0,<3.0)
Requires-Dist: astropy (>=5.3.3,<6) ; python_version < "3.10"
Requires-Dist: astropy (>=5.3.3,<7) ; python_version >= "3.10"
Requires-Dist: astropy-healpix (>=1.0,<2.0)
Requires-Dist: django-filter (>=23.0,<30.0)
Requires-Dist: django-webpack-loader (>=3.0,<4.0)
Requires-Dist: gracedb-sdk (<1)
Requires-Dist: healpix-alchemy (>=1.1.0,<2.0)
Requires-Dist: hop-client (>=0.10,<1.0)
Requires-Dist: ligo.skymap (>=2.1.0,<3.0)
Requires-Dist: psycopg2-binary (<3)
Requires-Dist: python-dateutil (<3)
Requires-Dist: tomtoolkit (>=2.24,<3)
